{
  "Workflows": [
    {
      "Path": null,
      "SortBy": 0,
      "VariablesSectionElementsOrder": [],
      "ArgumentsSectionElementsOrder": null,
      "ConstantsSectionElementsOrder": [],
      "AddedNamespaces": null
    },
    {
      "Path": "Temp/AppName_Action.xaml",
      "SortBy": 0,
      "VariablesSectionElementsOrder": [],
      "ArgumentsSectionElementsOrder": [
        "in_tsRetryInterval",
        "in_intRetryNum"
      ],
      "ConstantsSectionElementsOrder": [],
      "AddedNamespaces": null
    },
    {
      "Path": "IMDb/IMDb_LaunchApp.xaml",
      "SortBy": 0,
      "VariablesSectionElementsOrder": [],
      "ArgumentsSectionElementsOrder": [
        "out_Browser",
        "out_boolIMDbExist",
        "in_strURL",
        "in_tsRetryInterval",
        "in_intRetryNum"
      ],
      "ConstantsSectionElementsOrder": [],
      "AddedNamespaces": null
    },
    {
      "Path": "MainFlowChart.xaml",
      "SortBy": 0,
      "VariablesSectionElementsOrder": [
        "listMovies&Flowchart_1",
        "strAnswer&Flowchart_1",
        "dictMovie&Flowchart_1",
        "boolMovieExist&Flowchart_1",
        "strURL&Flowchart_1",
        "boolSearchPageExist&Flowchart_1",
        "strMovieName&Flowchart_1",
        "tsRetryInterval&Flowchart_1",
        "intRetryNum&Flowchart_1",
        "Browser&Flowchart_1",
        "boolIMDbExist&Flowchart_1"
      ],
      "ArgumentsSectionElementsOrder": [],
      "ConstantsSectionElementsOrder": [],
      "AddedNamespaces": null
    },
    {
      "Path": "IMDb/IMDb_SearchMovie.xaml",
      "SortBy": 0,
      "VariablesSectionElementsOrder": [
        "boolIMDbExists&Sequence_5"
      ],
      "ArgumentsSectionElementsOrder": [
        "out_boolSearchPageExist",
        "in_strMovieName",
        "in_intRetryNum",
        "in_tsRetryInterval"
      ],
      "ConstantsSectionElementsOrder": [],
      "AddedNamespaces": null
    },
    {
      "Path": "IMDb/IMDb_CheckMovieSearchResult.xaml",
      "SortBy": 0,
      "VariablesSectionElementsOrder": [
        "boolSearchPageExist&Sequence_5"
      ],
      "ArgumentsSectionElementsOrder": [
        "out_boolMovieExist",
        "in_intRetryNum",
        "in_tsRetryInterval"
      ],
      "ConstantsSectionElementsOrder": [],
      "AddedNamespaces": null
    },
    {
      "Path": "IMDb/IMDb_SelectMovie.xaml",
      "SortBy": 0,
      "VariablesSectionElementsOrder": [
        "boolMovieExist&Sequence_1"
      ],
      "ArgumentsSectionElementsOrder": [
        "out_boolMovieExists",
        "in_intRetryNum",
        "in_tsRetryInterval"
      ],
      "ConstantsSectionElementsOrder": [],
      "AddedNamespaces": null
    },
    {
      "Path": "IMDb/IMDb_ExtractMoieData.xaml",
      "SortBy": 0,
      "VariablesSectionElementsOrder": [
        "boolRateExists&Sequence_1",
        "boolTypeExists&Sequence_1",
        "boolTimeExists&Sequence_1",
        "boolYearExists&Sequence_1",
        "boolMovieExist&Sequence_5"
      ],
      "ArgumentsSectionElementsOrder": [
        "out_boolAllDataFound",
        "outBrowser",
        "out_dictMovie",
        "in_intRetryNum",
        "in_tsRetryInterval"
      ],
      "ConstantsSectionElementsOrder": [],
      "AddedNamespaces": null
    },
    {
      "Path": "Data/Data_SaveMovie.xaml",
      "SortBy": 0,
      "VariablesSectionElementsOrder": [],
      "ArgumentsSectionElementsOrder": [
        "in_strFilePath",
        "out_boolFileExists",
        "in_dictMovie",
        "in_intRetryNum",
        "in_tsRetryInterval"
      ],
      "ConstantsSectionElementsOrder": [],
      "AddedNamespaces": null
    },
    {
      "Path": "Data/Data_AppendMovieToHistory.xaml",
      "SortBy": 0,
      "VariablesSectionElementsOrder": [
        "strMovie&Sequence_6"
      ],
      "ArgumentsSectionElementsOrder": [
        "in_strFilePath",
        "in_listMovies",
        "in_intRetryNum",
        "in_tsRetryInterval",
        "out_boolFileExists"
      ],
      "ConstantsSectionElementsOrder": [],
      "AddedNamespaces": null
    },
    {
      "Path": "IMDb/IMDb_CloseBrowser.xaml",
      "SortBy": 0,
      "VariablesSectionElementsOrder": [],
      "ArgumentsSectionElementsOrder": [
        "in_intRetryNum",
        "in_tsRetryInterval"
      ],
      "ConstantsSectionElementsOrder": [],
      "AddedNamespaces": null
    },
    {
      "Path": "Main.xaml",
      "SortBy": 0,
      "VariablesSectionElementsOrder": [
        "tsRetryInterval&Sequence_1",
        "strMovieName&Sequence_1",
        "boolSearchPageExist&Sequence_1",
        "strURL&Sequence_1",
        "boolMovieExist&Sequence_1",
        "dictMovie&Sequence_1",
        "strAnswer&Sequence_1",
        "listMovies&Sequence_1",
        "strFolderPath&Flowchart_1",
        "boolFileExists&Flowchart_1",
        "boolIMDbExist&Flowchart_1",
        "Browser&Flowchart_1",
        "intRetryNum&Flowchart_1",
        "boolAllMovieDataExist&Flowchart_1"
      ],
      "ArgumentsSectionElementsOrder": [],
      "ConstantsSectionElementsOrder": [],
      "AddedNamespaces": null
    }
  ]
}